syndrilla/__init__.py
syndrilla/main.py
syndrilla/decoder/__init__.py
syndrilla/decoder/decoder.py
syndrilla/decoder/bp_branch_assisted/__init__.py
syndrilla/decoder/bp_branch_assisted/bp_branch_assisted.py
syndrilla/decoder/bp_lottery/__init__.py
syndrilla/decoder/bp_lottery/bp_lottery.py
syndrilla/decoder/bp_lottery_quant/__init__.py
syndrilla/decoder/bp_lottery_quant/bp_lottery_quant.py
syndrilla/decoder/bp_norm_min_sum/__init__.py
syndrilla/decoder/bp_norm_min_sum/bp_norm_min_sum.py
syndrilla/decoder/bp_norm_min_sum_quant/__init__.py
syndrilla/decoder/bp_norm_min_sum_quant/bp_norm_min_sum_quant.py
syndrilla/decoder/osd_0/osd_0.py
syndrilla/error_model/__init__.py
syndrilla/error_model/error_model.py
syndrilla/error_model/bsc/__init__.py
syndrilla/error_model/bsc/bsc.py
syndrilla/logical_check/__init__.py
syndrilla/logical_check/logical_check.py
syndrilla/logical_check/lx/__init__.py
syndrilla/logical_check/lx/lx.py
syndrilla/logical_check/lz/__init__.py
syndrilla/logical_check/lz/lz.py
syndrilla/matrix/__init__.py
syndrilla/matrix/matrix.py
syndrilla/matrix/alist/alist.py
syndrilla/matrix/npz/npz.py
syndrilla/matrix/txt/__init__.py
syndrilla/matrix/txt/txt.py
syndrilla/metric/__init__.py
syndrilla/metric/metric.py
syndrilla/syndrome/__init__.py
syndrilla/syndrome/syndrome.py
syndrilla/syndrome/perfect/__init__.py
syndrilla/syndrome/perfect/perfect.py
syndrilla/utils/__init__.py
syndrilla/utils/utils.py
syndrilla-2025.9.15.dist-info/METADATA
syndrilla-2025.9.15.dist-info/WHEEL
syndrilla-2025.9.15.dist-info/entry_points.txt
syndrilla-2025.9.15.dist-info/licenses/LICENSE
syndrilla-2025.9.15.dist-info/RECORD
