Metadata-Version: 2.4
Name: syndrilla
Version: 2025.9.15
Summary: A PyTorch-based numerical simulator for decoders in quantum error correction.
Project-URL: Homepage, https://github.com/UnaryLab/syndrilla
Project-URL: Issues, https://github.com/UnaryLab/syndrilla/issues
Author-email: Yanzhang Zhu <yanzhang.zhu@ucf.edu>, Di Wu <di.wu@ucf.edu>
License: MIT License
License-File: LICENSE
Classifier: Programming Language :: Python
Requires-Python: >=3.9
Requires-Dist: loguru
Requires-Dist: numpy
Requires-Dist: pyfiglet
Requires-Dist: pyyaml
Requires-Dist: scipy
Requires-Dist: torch>=2.0
Requires-Dist: yamlordereddictloader
